search_binary/__init__.py
search_binary/binary_search.py
search_binary-0.0.1.dist-info/LICENSE
search_binary-0.0.1.dist-info/METADATA
search_binary-0.0.1.dist-info/WHEEL
search_binary-0.0.1.dist-info/top_level.txt
search_binary-0.0.1.dist-info/RECORD
