Metadata-Version: 2.1
Name: search-binary
Version: 0.0.1
Summary: A binary search implementation in Python
Home-page: https://github.com/Shikha-code36/binary_search
Author: Shikha Pandey
Author-email: shikha.py36@gmail.com
License: MIT
Keywords: binary search algorithm,python,data-structures,algorithms,binary-search,searching-algorithm
Platform: UNKNOWN
Classifier: Development Status :: 3 - Alpha
Classifier: Intended Audience :: Developers
Classifier: Topic :: Software Development :: Libraries
Classifier: License :: OSI Approved :: MIT License
Classifier: Programming Language :: Python :: 3
Classifier: Programming Language :: Python :: 3.5
Classifier: Programming Language :: Python :: 3.6
Classifier: Programming Language :: Python :: 3.7
Classifier: Programming Language :: Python :: 3.8
License-File: LICENSE
